yace/__init__.py
yace/__main__.py
yace/compiler.py
yace/emitters.py
yace/errors.py
yace/model.py
yace/tools.py
yace/transformations.py
yace/cli/__init__.py
yace/cli/yace.py
yace/ir/__init__.py
yace/ir/base.py
yace/ir/constants.py
yace/ir/cparser.py
yace/ir/datatypes.py
yace/ir/derivedtypes.py
yace/ir/directives.py
yace/ir/functiontypes.py
yace/targets/__init__.py
yace/targets/collector.py
yace/targets/target.py
yace/targets/capi/__init__.py
yace/targets/capi/target.py
yace/targets/ctypes/__init__.py
yace/targets/ctypes/ctypes_sugar.py
yace/targets/ctypes/target.py
yace-0.5.7.dist-info/LICENSE
yace-0.5.7.dist-info/METADATA
yace-0.5.7.dist-info/WHEEL
yace-0.5.7.dist-info/entry_points.txt
yace-0.5.7.dist-info/top_level.txt
yace-0.5.7.dist-info/RECORD
