Metadata-Version: 2.1
Name: yace
Version: 0.5.7
Summary: yace aka Yet Another Code Emitter / Your Artisanal Code Emitter
Author-email: "Simon A. F. Lund" <os@safl.dk>
Maintainer-email: "Simon A. F. Lund" <os@safl.dk>
License:                     GNU GENERAL PUBLIC LICENSE
Classifier: Development Status :: 4 - Beta
Classifier: Environment :: Console
Classifier: Framework :: Pytest
Classifier: Intended Audience :: Developers
Classifier: Intended Audience :: System Administrators
Classifier: License :: OSI Approved :: GNU General Public License v2 (GPLv2)
Classifier: Programming Language :: Python :: 3
Classifier: Programming Language :: Python :: 3.7
Classifier: Programming Language :: Python :: 3.8
Classifier: Programming Language :: Python :: 3.9
Classifier: Programming Language :: Python :: 3.10
Classifier: Programming Language :: Python :: 3.11
Classifier: Topic :: Software Development :: Testing
Classifier: Topic :: Software Development
Classifier: Topic :: Text Processing
Classifier: Topic :: Utilities
Requires-Python: >=3.7
License-File: LICENSE
Requires-Dist: jinja2
Requires-Dist: pyyaml
Requires-Dist: pydantic
Requires-Dist: libclang~=14.0.1
Provides-Extra: dev
Requires-Dist: coverage; extra == "dev"
Requires-Dist: kmdo; extra == "dev"
Requires-Dist: pudb; extra == "dev"
Requires-Dist: sphinx; extra == "dev"
Requires-Dist: wheel; extra == "dev"
Provides-Extra: all
Requires-Dist: yace[dev]; extra == "all"
